llm_reflection/VERSION
llm_reflection/__init__.py
llm_reflection/llm_reflection.py
llm_reflection-0.1.0.dist-info/WHEEL
llm_reflection-0.1.0.dist-info/METADATA
llm_reflection-0.1.0.dist-info/RECORD
