Metadata-Version: 2.1
Name: llm-reflection
Version: 0.1.0
Summary: This system utilizes a large language model (LLM) and reflection
Author: jggomez
Author-email: juan.gomez01@gmail.com
Requires-Python: >=3.10,<4.0
Classifier: Programming Language :: Python :: 3
Classifier: Programming Language :: Python :: 3.10
Classifier: Programming Language :: Python :: 3.11
Requires-Dist: langchain-google-vertexai (>=1.0.6,<2.0.0)
Requires-Dist: langchain-openai (>=0.1.10,<0.2.0)
Requires-Dist: rich (>=13.7.1,<14.0.0)
